autogon_ml/__init__.py
autogon_ml/test.py
autogon_ml/autoClassification/__init__.py
autogon_ml/autoClassification/base.py
autogon_ml/autoFeatureEngineering/__init__.py
autogon_ml/autoFeatureEngineering/base.py
autogon_ml/autoRegression/__init__.py
autogon_ml/autoRegression/base.py
autogon_ml/auto_data_preprocessing/__init__.py
autogon_ml/auto_data_preprocessing/AutoClean/__init__.py
autogon_ml/auto_data_preprocessing/AutoClean/autoclean.py
autogon_ml/auto_data_preprocessing/AutoClean/modules.py
autogon_ml/auto_data_preprocessing/feature_engineering/__init__.py
autogon_ml/auto_data_preprocessing/feature_engineering/base.py
autogon_ml/auto_data_preprocessing/feature_engineering/util.py
eobi-1.1.4.dist-info/METADATA
eobi-1.1.4.dist-info/WHEEL
eobi-1.1.4.dist-info/top_level.txt
eobi-1.1.4.dist-info/RECORD
