Metadata-Version: 2.1
Name: eobi
Version: 1.1.4
Summary: ...
Author: Autogon Inc
Author-email: developer@autogon.ai
Classifier: License :: OSI Approved :: MIT License
Classifier: Programming Language :: Python :: 3
Classifier: Programming Language :: Python :: 3.6
Classifier: Programming Language :: Python :: 3.7
Classifier: Programming Language :: Python :: 3.8
Classifier: Programming Language :: Python :: 3.9
Requires-Dist: catboost
Requires-Dist: contourpy
Requires-Dist: cycler
Requires-Dist: fonttools
Requires-Dist: graphviz
Requires-Dist: joblib
Requires-Dist: kiwisolver
Requires-Dist: lightgbm
Requires-Dist: matplotlib
Requires-Dist: numpy
Requires-Dist: packaging
Requires-Dist: pandas
Requires-Dist: Pillow
Requires-Dist: plotly
Requires-Dist: pyparsing
Requires-Dist: python-dateutil
Requires-Dist: pytz
Requires-Dist: scikit-learn
Requires-Dist: scipy
Requires-Dist: six
Requires-Dist: tenacity
Requires-Dist: threadpoolctl
Requires-Dist: tzdata
Requires-Dist: xgboost
Requires-Dist: dataprep
Requires-Dist: py-AutoClean
